{
    "0": {
        "quest": "<p>Which of the following alcohol is unable to turn orange colour of chromic acid to green?\n</p>",
        "option_1": "1\u00b0 alcohol",
        "option_2": "2\u00b0 alcohol",
        "option_3": "3\u00b0 alcohol",
        "option_4": "Allyl alcohol",
        "correct_ans": "3"
    },
    "1": {
        "quest": "<p>Lucas test is associated with</p>",
        "option_1": "aldehydes",
        "option_2": "phenols",
        "option_3": "carboxylic acids",
        "option_4": "alcohols",
        "correct_ans": "4"
    },
    "2": {
        "quest": "<p>Which one can differentiate between C<sub>2</sub>H<sub>5</sub>OH and CH<sub>3</sub>OH ?\n</p>",
        "option_1": "H<sub>2</sub>O",
        "option_2": "Na<sub>2</sub>CO<sub>3</sub> + I<sub>2</sub>",
        "option_3": "NH<sub>3</sub>",
        "option_4": "HCl",
        "correct_ans": "2"
    },
    "3": {
        "quest": "<p>Iodoform reaction is answered by all, except</p>",
        "option_1": "\t\t1) <img src=\"https://jeefocus.com/assets/images/question/2/Sec2Cat55SubCat216Q96O1.png\"/>",
        "option_2": "CH<sub>3</sub>CHO",
        "option_3": "CH<sub>3</sub>\u2014CH<sub>2</sub>\u2014OH",
        "option_4": "CH<sub>3</sub>\u2014CH<sub>2</sub> \u2014CH<sub>2</sub>OH",
        "correct_ans": "4"
    },
    "4": {
        "quest": "<p>An unknown alcohol is treated with the \"Lucas reagent\" to determine wheter the alcohol is primary, secondary or tertiary. Which alcohol reacts fastest and by what mechanism?\n</p>",
        "option_1": "Secondary alcohol by S<sub>N</sub>1",
        "option_2": "Tertiary alcohol by S<sub>N</sub>2",
        "option_3": "Secondary alcohol by S<sub>N</sub>2",
        "option_4": "Tertiary alcohol by S<sub>N</sub>1",
        "correct_ans": "4"
    },
    "5": {
        "quest": "<p>Upon treatment with I<sub>2</sub> and aqueous NaOH, which of the following compounds will form iodoform?\n</p>",
        "option_1": "CH<sub>3</sub>CH<sub>2</sub>CH<sub>2</sub>CH<sub>2</sub>CHO",
        "option_2": "CH<sub>3</sub>CH<sub>2</sub> COCH<sub>2</sub>CH<sub>3</sub> ",
        "option_3": "CH<sub>3</sub>CH<sub>2</sub>CH<sub>2</sub>CH<sub>2</sub>CH<sub>2</sub>OH",
        "option_4": "CH<sub>3</sub>CH<sub>2</sub>CH<sub>2</sub>CH (OH) CH<sub>3</sub> ",
        "correct_ans": "4"
    },
    "6": {
        "quest": "<p>The compound which gives turbidity immediately with Lucas reagent at room temperature is\n</p>",
        "option_1": "butan-1-ol",
        "option_2": "butan-2 -ol",
        "option_3": "2-methyl propan-2-ol ",
        "option_4": "2-methyl propan-1-ol",
        "correct_ans": "3"
    },
    "7": {
        "quest": "<p>The function of ZnCl<sub>2</sub> in Lucas test for alcohols is </p>",
        "option_1": "to act as acid catalyst and react with HCl to form  H<sub>2</sub> ZnCl<sub>4</sub>",
        "option_2": "to act as base catalyst and react with NaOH to form Na<sub>2</sub>Zn(OH)<sub>4</sub> ",
        "option_3": "to act as amphoteric catalyst",
        "option_4": "to act as neutral catalyst",
        "correct_ans": "1"
    },
    "8": {
        "quest": "<p>Primary, secondary and tertiary alcohols are distinguished from one another by\n</p>",
        "option_1": "Ninhydrin test",
        "option_2": "Tollen's reagent",
        "option_3": "Lucas test",
        "option_4": "Wittig reaction ",
        "correct_ans": "3"
    },
    "9": {
        "quest": "<p>In Lucas test an alcohol reacts immediately and gives insoluble chloride. The alcohol is\n</p>",
        "option_1": "CH<sub>3</sub>OH",
        "option_2": "CH<sub>3</sub>CH<sub>2</sub>OH",
        "option_3": "(CH<sub>3</sub>)<sub>2</sub>CHOH",
        "option_4": "(CH<sub>3</sub>)<sub>3</sub>COH",
        "correct_ans": "3"
    },
    "10": {
        "quest": "<p>Lucas reagent is</p>",
        "option_1": "conc. HCl and anhydrous ZnCl<sub>2</sub> ",
        "option_2": "conc. HNO<sub>3</sub> and hydrous ZnCl<sub>2</sub>",
        "option_3": "conc. HCl and hydrous ZnCl<sub>2</sub> ",
        "option_4": "conc. HNO<sub>3</sub>  and anhydrous ZnCl<sub>2</sub>",
        "correct_ans": "1"
    },
    "11": {
        "quest": "<p>Which of the following compounds is most acidic ?</p>",
        "option_1": "CH<sub>4</sub>",
        "option_2": "C<sub>2</sub>H<sub>6</sub>",
        "option_3": "CH \u2261 CH",
        "option_4": "C<sub>2</sub>H<sub>5</sub>OH",
        "correct_ans": "4"
    },
    "12": {
        "quest": "<p>Which of the following compounds will give positive iodoform test with I<sub>2</sub> and NaOH ?</p>",
        "option_1": "C<sub>6</sub> H<sub>5</sub> COC<sub>6</sub> H<sub>5</sub>",
        "option_2": "CH<sub>3</sub>CH<sub>2</sub>CHO",
        "option_3": "C<sub>6</sub>H<sub>5</sub>COCH<sub>2</sub>CH<sub>3</sub>",
        "option_4": "\t\t4) <img src=\"https://jeefocus.com/assets/images/question/2/Sec2Cat55SubCat216Q91O4.png\"/>",
        "correct_ans": "4"
    }
}